Kam_Ultimate_Reporter/__init__.py
Kam_Ultimate_Reporter/bibliographic.py
Kam_Ultimate_Reporter/functions.py
Kam_Ultimate_Reporter/main.py
Kam_Ultimate_Reporter/report_generator.py
Kam_Ultimate_Reporter-0.0.8.dist-info/LICENSE
Kam_Ultimate_Reporter-0.0.8.dist-info/METADATA
Kam_Ultimate_Reporter-0.0.8.dist-info/WHEEL
Kam_Ultimate_Reporter-0.0.8.dist-info/entry_points.txt
Kam_Ultimate_Reporter-0.0.8.dist-info/top_level.txt
Kam_Ultimate_Reporter-0.0.8.dist-info/RECORD
